Metadata-Version: 2.1
Name: usefulfunctionsbyjoci
Version: 0.0.4
Summary: Useful functions
Home-page: UNKNOWN
Author: Joci12
Author-email: <csutak.jozsef.lorant.86@gmail.com>
License: UNKNOWN
Keywords: python,useful,function,usefull functions,joci,package
Platform: UNKNOWN
Classifier: Programming Language :: Python :: 3
